{
  "slug": "radish",
  "name": "だいこん",
  "emoji": "🥬",
  "category": "根菜",
  "unit": "円/kg",
  "source": "retail",
  "updatedAt": "2026-07-16T22:57:01.624Z",
  "cities": [
    {
      "citySlug": "sapporo",
      "cityName": "札幌市",
      "series": [
        {
          "date": "2026-04-01",
          "price": 197.21040731247064
        },
        {
          "date": "2026-05-01",
          "price": 217.7358287721318
        },
        {
          "date": "2026-06-01",
          "price": 166.23135181985177
        }
      ]
    },
    {
      "citySlug": "sendai",
      "cityName": "仙台市",
      "series": [
        {
          "date": "2026-04-01",
          "price": 160.8649726187013
        },
        {
          "date": "2026-05-01",
          "price": 178.5391451401305
        },
        {
          "date": "2026-06-01",
          "price": 169.94115290813286
        }
      ]
    },
    {
      "citySlug": "tokyo",
      "cityName": "東京23区",
      "series": [
        {
          "date": "2026-04-01",
          "price": 154.1237523669042
        },
        {
          "date": "2026-05-01",
          "price": 187.09909217843924
        },
        {
          "date": "2026-06-01",
          "price": 177.64830854013252
        }
      ]
    },
    {
      "citySlug": "kanazawa",
      "cityName": "金沢市",
      "series": [
        {
          "date": "2026-04-01",
          "price": 191.62169720342393
        },
        {
          "date": "2026-05-01",
          "price": 206.47993185659834
        },
        {
          "date": "2026-06-01",
          "price": 200.63700545800882
        }
      ]
    },
    {
      "citySlug": "nagoya",
      "cityName": "名古屋市",
      "series": [
        {
          "date": "2026-04-01",
          "price": 164.3814331670794
        },
        {
          "date": "2026-05-01",
          "price": 179.82604438910013
        },
        {
          "date": "2026-06-01",
          "price": 209.2186875492006
        }
      ]
    },
    {
      "citySlug": "osaka",
      "cityName": "大阪市",
      "series": [
        {
          "date": "2026-04-01",
          "price": 208.1269053122654
        },
        {
          "date": "2026-05-01",
          "price": 220.40730699851247
        },
        {
          "date": "2026-06-01",
          "price": 226.6329886101057
        }
      ]
    },
    {
      "citySlug": "hiroshima",
      "cityName": "広島市",
      "series": [
        {
          "date": "2026-04-01",
          "price": 206.80139643513425
        },
        {
          "date": "2026-05-01",
          "price": 200.87269086753605
        },
        {
          "date": "2026-06-01",
          "price": 231.71725282670968
        }
      ]
    },
    {
      "citySlug": "takamatsu",
      "cityName": "高松市",
      "series": [
        {
          "date": "2026-04-01",
          "price": 132.95427331703738
        },
        {
          "date": "2026-05-01",
          "price": 143.82048265614304
        },
        {
          "date": "2026-06-01",
          "price": 209.4736256357159
        }
      ]
    },
    {
      "citySlug": "fukuoka",
      "cityName": "福岡市",
      "series": [
        {
          "date": "2026-04-01",
          "price": 138.02510477541293
        },
        {
          "date": "2026-05-01",
          "price": 202.62775151123805
        },
        {
          "date": "2026-06-01",
          "price": 206.81202010272187
        }
      ]
    },
    {
      "citySlug": "national",
      "cityName": "全国",
      "series": [
        {
          "date": "2026-04-01",
          "price": 172.6788825009366
        },
        {
          "date": "2026-05-01",
          "price": 193.04536381887
        },
        {
          "date": "2026-06-01",
          "price": 199.81248816117554
        }
      ]
    }
  ]
}
